datasette_auth_tokens/__init__.py
datasette_auth_tokens-0.3.dist-info/LICENSE
datasette_auth_tokens-0.3.dist-info/METADATA
datasette_auth_tokens-0.3.dist-info/WHEEL
datasette_auth_tokens-0.3.dist-info/entry_points.txt
datasette_auth_tokens-0.3.dist-info/top_level.txt
datasette_auth_tokens-0.3.dist-info/RECORD
