Metadata-Version: 2.1
Name: datasette-auth-tokens
Version: 0.3
Summary: Datasette plugin for authenticating access using API tokens
Home-page: https://github.com/simonw/datasette-auth-tokens
Author: Simon Willison
License: Apache License, Version 2.0
Project-URL: Issues, https://github.com/simonw/datasette-auth-tokens/issues
Project-URL: CI, https://github.com/simonw/datasette-auth-tokens/actions
Project-URL: Changelog, https://github.com/simonw/datasette-auth-tokens/releases
Platform: UNKNOWN
License-File: LICENSE
Requires-Dist: datasette (>=0.44)
Provides-Extra: test
Requires-Dist: pytest ; extra == 'test'
Requires-Dist: pytest-asyncio ; extra == 'test'
Requires-Dist: httpx ; extra == 'test'
Requires-Dist: sqlite-utils ; extra == 'test'
